<?xml version="1.0" encoding="UTF-8"?>
<objects serializationModel="Studio.02.02.00">
	<object class="EncodingSetting" id="{e71c6079-0d36-40b2-a1ac-0ee89abef4c1}">
		<property name="encodingFormat">
			<value>3</value>
		</property>
		<property name="quality">
			<value>37</value>
		</property>
		<relationship name="platform">
			<destination>{8cfc1638-9287-423b-a187-e529d78dc1ea}</destination>
		</relationship>
		<relationship name="encodable">
			<destination>{8cfc1638-9287-423b-a187-e529d78dc1ea}</destination>
		</relationship>
	</object>
</objects>
